CHANGES.rst
CONTRIBUTORS.rst
DEVELOP.rst
LICENSE.GPL
LICENSE.rst
MANIFEST.in
README.rst
requirements.txt
setup.cfg
setup.py
docs/index.rst
src/imioweb/__init__.py
src/imioweb.policy.egg-info/PKG-INFO
src/imioweb.policy.egg-info/SOURCES.txt
src/imioweb.policy.egg-info/dependency_links.txt
src/imioweb.policy.egg-info/entry_points.txt
src/imioweb.policy.egg-info/namespace_packages.txt
src/imioweb.policy.egg-info/not-zip-safe
src/imioweb.policy.egg-info/requires.txt
src/imioweb.policy.egg-info/top_level.txt
src/imioweb/policy/__init__.py
src/imioweb/policy/configure.zcml
src/imioweb/policy/interfaces.py
src/imioweb/policy/permissions.zcml
src/imioweb/policy/setuphandlers.py
src/imioweb/policy/testing.py
src/imioweb/policy/upgrades.py
src/imioweb/policy/upgrades.zcml
src/imioweb/policy/browser/__init__.py
src/imioweb/policy/browser/configure.zcml
src/imioweb/policy/browser/overrides/.gitkeep
src/imioweb/policy/browser/static/.gitkeep
src/imioweb/policy/locales/library.policy.pot
src/imioweb/policy/locales/update.sh
src/imioweb/policy/profiles/default/browserlayer.xml
src/imioweb/policy/profiles/default/catalog.xml
src/imioweb/policy/profiles/default/metadata.xml
src/imioweb/policy/profiles/default/registry.xml
src/imioweb/policy/profiles/default/rolemap.xml
src/imioweb/policy/profiles/uninstall/browserlayer.xml
src/imioweb/policy/tests/__init__.py
src/imioweb/policy/tests/test_robot.py
src/imioweb/policy/tests/test_setup.py
src/imioweb/policy/tests/robot/test_example.robot