Metadata-Version: 2.1
Name: imioweb.policy
Version: 1.0b9
Summary: Policy for the installation of buildout.imioweb
Home-page: https://pypi.python.org/pypi/imioweb.policy
Author: Nicolas Demonte
Author-email: support@imio.be
License: GPL version 2
Keywords: Python Plone
Platform: UNKNOWN
Classifier: Environment :: Web Environment
Classifier: Framework :: Plone
Classifier: Framework :: Plone :: 5.2
Classifier: Programming Language :: Python
Classifier: Programming Language :: Python :: 3.6
Classifier: Programming Language :: Python :: 3.7
Classifier: Operating System :: OS Independent
Classifier: License :: OSI Approved :: GNU General Public License v2 (GPLv2)
Provides-Extra: test
